seacharts/__init__.py
seacharts/config.yaml
seacharts/config_schema.yaml
seacharts/enc.py
seacharts/display/__init__.py
seacharts/display/colors.py
seacharts/display/display.py
seacharts/display/events.py
seacharts/display/features.py
seacharts/environment/__init__.py
seacharts/environment/environment.py
seacharts/environment/extent.py
seacharts/environment/scope.py
seacharts/spatial/__init__.py
seacharts/spatial/base.py
seacharts/spatial/hypsometry.py
seacharts/spatial/layers.py
seacharts/spatial/shapes.py
seacharts/utils/__init__.py
seacharts/utils/config.py
seacharts/utils/files.py
seacharts/utils/parser.py
seacharts/utils/paths.py
seacharts-3.0.0.dist-info/LICENSE
seacharts-3.0.0.dist-info/METADATA
seacharts-3.0.0.dist-info/WHEEL
seacharts-3.0.0.dist-info/top_level.txt
seacharts-3.0.0.dist-info/RECORD
