Metadata-Version: 2.1
Name: seacharts
Version: 3.0.0
Summary: Electronic navigational charts (ENCs) processing & visualization
Home-page: https://github.com/simbli/seacharts
Author: Simon Blindheim, Trym Tengesdal
Author-email: simon.blindheim@ntnu.no
Project-URL: Bug Tracker, https://github.com/simbli/seacharts/issues
Keywords: api,ships,sea charts,visualization,electronic navigational charts
Classifier: Development Status :: 3 - Alpha
Classifier: Intended Audience :: Developers
Classifier: License :: OSI Approved :: MIT License
Classifier: Programming Language :: Python :: 3 :: Only
Classifier: Programming Language :: Python :: 3.11
Requires-Python: >=3.11
License-File: LICENSE
Requires-Dist: numpy
Requires-Dist: gdal
Requires-Dist: fiona
Requires-Dist: cartopy
Requires-Dist: shapely
Requires-Dist: matplotlib
Requires-Dist: matplotlib-scalebar
Requires-Dist: cerberus
Requires-Dist: pyyaml
